topolearn/__init__.py
topolearn/topolearn.pkl
topolearn/topolearn.py
topolearn-0.1.0.dist-info/licenses/LICENSE
topolearn-0.1.0.dist-info/METADATA
topolearn-0.1.0.dist-info/WHEEL
topolearn-0.1.0.dist-info/top_level.txt
topolearn-0.1.0.dist-info/RECORD
