Metadata-Version: 2.4
Name: topolearn
Version: 0.1.0
Summary: Topolearn score computed using persistent homology
Home-page: https://github.com/Boehringer-Ingelheim/topolearn
Author: Florian Rottach
Author-email: florianrottach@gmail.com
License: MIT
Classifier: Intended Audience :: Science/Research
Classifier: License :: OSI Approved :: MIT License
Classifier: Operating System :: POSIX :: Linux
Classifier: Programming Language :: Python :: 3.11
License-File: LICENSE
Requires-Dist: numpy==1.26.4
Requires-Dist: ripser==0.6.8
Requires-Dist: giotto-tda==0.6.0
Requires-Dist: pandas==2.0.0
Requires-Dist: scikit-learn==1.5.1
Dynamic: author
Dynamic: author-email
Dynamic: classifier
Dynamic: home-page
Dynamic: license
Dynamic: license-file
Dynamic: requires-dist
Dynamic: summary
